lifelogger/__init__.py
lifelogger/__main__.py
lifelogger/client_secrets.json
lifelogger/config.py
lifelogger/connection.py
lifelogger/database.py
lifelogger/main.py
lifelogger/utils.py
lifelogger/commands/__init__.py
lifelogger/commands/google.py
lifelogger/commands/local.py
lifelogger/commands/parser.py
lifelogger-0.2.2.dist-info/DESCRIPTION.rst
lifelogger-0.2.2.dist-info/METADATA
lifelogger-0.2.2.dist-info/RECORD
lifelogger-0.2.2.dist-info/WHEEL
lifelogger-0.2.2.dist-info/entry_points.txt
lifelogger-0.2.2.dist-info/metadata.json
lifelogger-0.2.2.dist-info/top_level.txt
