Metadata-Version: 2.0
Name: lifelogger
Version: 0.2.2
Summary: Track your life like a pro on Google Calendar via your terminal.
Home-page: https://github.com/adamchainz/lifelogger
Author: adamchainz
Author-email: me@adamj.eu
License: MIT
Platform: UNKNOWN
Classifier: Development Status :: 5 - Production/Stable
Classifier: Environment :: Console
Classifier: License :: OSI Approved :: MIT License
Classifier: Natural Language :: English
Classifier: Operating System :: OS Independent
Classifier: Programming Language :: Python :: 2
Classifier: Programming Language :: Python :: 2.7
Classifier: Programming Language :: Python
Classifier: Topic :: Software Development
Classifier: Topic :: Office/Business :: Scheduling
Requires-Dist: python-dateutil
Requires-Dist: google-api-python-client
Requires-Dist: icalendar
Requires-Dist: peewee (<3)
Requires-Dist: requests
Requires-Dist: termcolor
